moocloze/__init__.py
moocloze/moocloze.py
moocloze-1.0.2.dist-info/LICENSE
moocloze-1.0.2.dist-info/METADATA
moocloze-1.0.2.dist-info/WHEEL
moocloze-1.0.2.dist-info/top_level.txt
moocloze-1.0.2.dist-info/RECORD
