Metadata-Version: 2.1
Name: moocloze
Version: 1.0.2
Summary: Python library to populate Moodle question banks using a Cloze/XML format.
Home-page: https://github.com/miguelinux314/moocloze
Download-URL: https://github.com/miguelinux314/moocloze/archive/v1.0.2.tar.gz
Author: Miguel Hernandez Cabronero
Author-email: miguel.hernandez@uab.cat
License: MIT License
Platform: any
Classifier: Programming Language :: Python
Classifier: Development Status :: 5 - Production/Stable
Classifier: Natural Language :: English
Classifier: Environment :: Console
Classifier: Intended Audience :: Developers
Classifier: License :: OSI Approved :: MIT License
Classifier: Operating System :: OS Independent
Classifier: Programming Language :: Python :: 3
Classifier: Topic :: Scientific/Engineering
Requires-Python: >=3.6
License-File: LICENSE
